lambdaq/VERSION
lambdaq/__init__.py
lambdaq/event_handler.py
lambdaq/handle_event.py
lambdaq/logging.py
lambdaq/metadata.py
lambdaq/py.typed
lambdaq/types/__init__.py
lambdaq/types/message.py
lambdaq/types/message_handler.py
lambdaq/types/py.typed
lambdaq/types/response.py
lambdaq-2.0.0.dist-info/LICENSE
lambdaq-2.0.0.dist-info/METADATA
lambdaq-2.0.0.dist-info/WHEEL
lambdaq-2.0.0.dist-info/top_level.txt
lambdaq-2.0.0.dist-info/RECORD
