Metadata-Version: 2.1
Name: lambdaq
Version: 2.0.0
Summary: Helps you write Amazon Web Services Lambda functions called by Step Functions via SQS
Author: Cariad Eccleston
Author-email: cariad@cariad.earth
License: MIT
Project-URL: Project, https://github.com/cariad/lambdaq
Classifier: Development Status :: 5 - Production/Stable
Classifier: License :: OSI Approved :: MIT License
Classifier: Natural Language :: English
Classifier: Operating System :: OS Independent
Classifier: Programming Language :: Python :: 3 :: Only
Classifier: Programming Language :: Python :: 3.10
Classifier: Programming Language :: Python :: 3.11
Classifier: Programming Language :: Python :: 3.12
Classifier: Typing :: Typed
Requires-Python: >=3.10
License-File: LICENSE
Requires-Dist: boto3 ~=1.0
